aib/__init__.py
aib/_private/__init__.py
aib/_private/client.py
aib/_private/exceptions.py
aib/_private/utils/VO.py
aib/_private/utils/__init__.py
aib/_private/utils/utils.py
aib/data/__init__.py
aib/data/dataset.py
aib/data/read_api.py
aib/pipeline/__init__.py
aib/pipeline/api.py
aib/pipeline/artifacts.py
aib/pipeline/component.py
aib/pipeline/exceptions.py
aib/pipeline/pipeline.py
aib/pipeline/utils.py
aib/train/__init__.py
aib/train/api.py
aib/train/sklearn.py
aib/train/train_result.py
aib/train/types.py
aib/train/xgboost.py
aib/tune/__init__.py
aib/tune/api.py
aib_test-0.2.7.dist-info/METADATA
aib_test-0.2.7.dist-info/WHEEL
aib_test-0.2.7.dist-info/top_level.txt
aib_test-0.2.7.dist-info/RECORD
